lazy_bear/__init__.py
lazy_bear/__main__.py
lazy_bear/_logger.py
lazy_bear/lazy_attribute.py
lazy_bear/lazy_imports.py
lazy_bear/py.typed
lazy_bear/_internal/__init__.py
lazy_bear/_internal/_cmds.py
lazy_bear/_internal/_exit_code.py
lazy_bear/_internal/_info.py
lazy_bear/_internal/_version.py
lazy_bear/_internal/_version.pyi
lazy_bear/_internal/cli.py
lazy_bear/_internal/debug.py
lazy_bear-0.0.11.dist-info/METADATA
lazy_bear-0.0.11.dist-info/WHEEL
lazy_bear-0.0.11.dist-info/entry_points.txt
lazy_bear-0.0.11.dist-info/RECORD
