Metadata-Version: 2.4
Name: lazy-bear
Version: 0.0.11
Summary: A lazy import package for both modules and items within modules.
Author-email: chaz <bright.lid5647@fastmail.com>
Requires-Python: >=3.12
